{
  "campaigns": [
    {
      "id": "camp-svx-001",
      "title": "SVX — Webinar Re-engagement",
      "targetAudience": "Webinar partner orgs",
      "type": "email",
      "channel": "Email",
      "status": "pending",
      "pushedDate": "Apr 2026",
      "from": "Keyona",
      "contactOrg": "SVX",
      "contactPerson": "James",
      "sc_contact_id": "C1775180494358",
      "sc_initiative_id": "INI-1775180449939",
      "outreachStatus": "waiting",
      "waitingOn": "James's response. Sent by Keyona Apr 6 2026.",
      "sent": true,
      "emailSubject": "Picking back up — webinar idea for your community"
    },
    {
      "id": "camp-ctn-octia-001",
      "title": "Bryan Watson — Clean Tech North + OCTIA Webinar Pitch",
      "targetAudience": "Webinar partner orgs",
      "type": "email",
      "channel": "Email",
      "status": "pending",
      "pushedDate": "Apr 2026",
      "from": "Keyona",
      "contactOrg": "Clean Tech North + OCTIA",
      "contactPerson": "Bryan Watson",
      "sc_contact_id": "C1775180511190",
      "sc_initiative_id": "INI-1775180449939",
      "outreachStatus": "waiting",
      "waitingOn": "In active email chain. Possible call coming.",
      "sent": true,
      "emailSubject": "Webinar collab — want to co-host one session?"
    },
    {
      "id": "camp-cafiid-001",
      "title": "CAFIID — Webinar Pitch",
      "targetAudience": "Webinar partner orgs",
      "type": "email",
      "channel": "Email",
      "status": "pending",
      "pushedDate": "Apr 2026",
      "from": "Bryan Duarte",
      "contactOrg": "CAFIID",
      "sc_contact_id": "C1775180512231",
      "sc_initiative_id": "INI-1775180449939",
      "outreachStatus": "waiting",
      "waitingOn": "Bryan to identify right contact via CAFIID membership.",
      "sent": false,
      "emailSubject": "Webinar collab — climate tech exits for your community"
    },
    {
      "id": "camp-goodinvestor-001",
      "title": "Good Investor (Tim) — Webinar Pitch",
      "targetAudience": "Webinar partner orgs",
      "type": "email",
      "channel": "Email",
      "status": "pending",
      "pushedDate": "Apr 2026",
      "from": "Bryan Duarte",
      "contactOrg": "Good Investor",
      "sc_contact_id": "C1775180513230",
      "sc_initiative_id": "INI-1775180449939",
      "outreachStatus": "blocked",
      "blocker": "On hold until LPA signed and BTC site live. Bryan's call.",
      "sent": false
    },
    {
      "id": "camp-boann-001",
      "title": "Boann — Fund Re-engagement",
      "targetAudience": "Institutional investors — Canadian",
      "type": "email",
      "channel": "Email",
      "status": "pending",
      "pushedDate": "Apr 2026",
      "from": "Keyona",
      "contactOrg": "Boann",
      "contactPerson": "Emma",
      "sc_contact_id": "C1775180534166",
      "sc_initiative_id": "INI-1775180457900",
      "outreachStatus": "waiting",
      "waitingOn": "Bryan Duarte greenlight pending.",
      "sent": false,
      "emailSubject": "New Fund Updates from BlackTech Capital (climate fund)"
    },
    {
      "id": "camp-atmospheric-001",
      "title": "Atmospheric Fund — ABM First Touch",
      "targetAudience": "Institutional investors — Canadian",
      "type": "email",
      "channel": "Email",
      "status": "pending",
      "pushedDate": "Apr 2026",
      "from": "Bryan Duarte",
      "contactOrg": "The Atmospheric Fund",
      "contactPerson": "Uzoma Erondu",
      "contactEmail": "uerondu@taf.ca",
      "sc_contact_id": "C1775180533154",
      "sc_initiative_id": "INI-1775180457900",
      "outreachStatus": "waiting",
      "waitingOn": "Sent to Bryan Apr 7 2026. Bryan sending directly.",
      "sent": false,
      "emailSubject": "Still thinking about that SVX overlap"
    },
    {
      "id": "camp-toronto-foundation-001",
      "title": "Toronto Foundation — ABM First Touch",
      "targetAudience": "Institutional investors — Canadian",
      "type": "email",
      "channel": "Email",
      "status": "pending",
      "pushedDate": "Apr 2026",
      "from": "Bryan Duarte",
      "contactOrg": "Toronto Foundation",
      "contactPerson": "Rashid Javed",
      "contactEmail": "rjaved@torontofoundation.ca",
      "sc_contact_id": "C1775180531700",
      "sc_initiative_id": "INI-1775180457900",
      "outreachStatus": "waiting",
      "waitingOn": "Sent to Bryan Apr 7 2026. Bryan sending directly.",
      "sent": false,
      "emailSubject": "Long overdue catch-up"
    },
    {
      "id": "camp-btc-compliance-001",
      "title": "BTC Compliance Calendar — TIP Member Feedback Follow-up",
      "type": "email",
      "channel": "Email",
      "status": "pending",
      "pushedDate": "Apr 2026",
      "from": "Keyona",
      "sc_initiative_id": "INI-003",
      "outreachStatus": "waiting",
      "sent": false
    },
    {
      "id": "el-camp-ici-001",
      "title": "ICI — Shardul Dabir — Exit Lab",
      "type": "linkedin",
      "channel": "LinkedIn",
      "status": "pending",
      "pushedDate": "Apr 2026",
      "from": "Keyona",
      "contactPerson": "Shardul Dabir",
      "sc_contact_id": "CTEL-shardul-dabir-2026",
      "sc_initiative_id": "INI-001",
      "outreachStatus": "waiting_on_acceptance",
      "sent": false,
      "gmailLabel": "CTEL_Webinar_Collab"
    },
    {
      "id": "el-camp-thruline-001",
      "title": "Thruline Thursdays — Exit Lab Guest",
      "type": "email",
      "channel": "Email",
      "status": "pending",
      "pushedDate": "Apr 2026",
      "from": "Keyona",
      "sc_initiative_id": "INI-1775180449939",
      "outreachStatus": "needs_send",
      "sent": false
    },
    {
      "id": "el-camp-carbonequity-001",
      "title": "Carbon Equity — Shayle Kann Intro",
      "type": "email",
      "channel": "Email",
      "status": "pending",
      "pushedDate": "Apr 2026",
      "from": "Keyona",
      "sc_initiative_id": "INI-1775180449939",
      "outreachStatus": "needs_send",
      "sent": false
    },
    {
      "id": "el-camp-cleanupmarketing-001",
      "title": "Clean Up Marketing — Shari Sentlowitz",
      "type": "email",
      "channel": "Email",
      "status": "sent",
      "pushedDate": "Apr 2026",
      "from": "Keyona",
      "contactPerson": "Shari Sentlowitz",
      "contactEmail": "info@cleanupmarketing.com",
      "sc_contact_id": "CTEL-shari-sentlowitz-2026",
      "sc_initiative_id": "INI-001",
      "outreachStatus": "waiting",
      "sent": true,
      "gmailLabel": "CTEL_Webinar_Collab",
      "emailSubject": "your April 15 webinar + a project I'm working on"
    },
    {
      "id": "el-camp-nyas-001",
      "title": "NYAS — Climate Tech Investing Panel",
      "type": "email",
      "channel": "Email",
      "status": "pending",
      "pushedDate": "Apr 2026",
      "from": "Keyona",
      "sc_initiative_id": "INI-1775180449939",
      "outreachStatus": "needs_send",
      "sent": false
    },
    {
      "id": "el-camp-netzeroangels-001",
      "title": "Net Zero Angels — Guest Spot",
      "type": "email",
      "channel": "Email",
      "status": "pending",
      "pushedDate": "Apr 2026",
      "from": "Keyona",
      "sc_initiative_id": "INI-1775180449939",
      "outreachStatus": "needs_send",
      "sent": false
    },
    {
      "id": "ctel-b1-karen-sheffield",
      "title": "Karen Sheffield — Pachamama Ventures",
      "type": "email",
      "channel": "Email",
      "status": "sent",
      "pushedDate": "Apr 2026",
      "from": "Keyona",
      "contactPerson": "Karen Sheffield",
      "sc_contact_id": "C1773968001265",
      "sc_initiative_id": "INI-001",
      "outreachStatus": "waiting",
      "sent": true,
      "gmailLabel": "CTEL_Webinar_Collab"
    },
    {
      "id": "ctel-b1-jack-rusk",
      "title": "Jack Rusk — C.Scale",
      "type": "email",
      "channel": "Email",
      "status": "in_progress",
      "pushedDate": "Apr 2026",
      "from": "Keyona",
      "contactPerson": "Jack Rusk",
      "contactEmail": "jack@cscale.io",
      "sc_contact_id": "CTEL-jack-rusk-2026",
      "sc_initiative_id": "INI-001",
      "outreachStatus": "replied",
      "waitingOn": "Jack replied. Keyona sent follow-up clarifying Exit Lab angle and no pay-to-play. Awaiting Jack's next response.",
      "sent": true,
      "gmailLabel": "CTEL_Webinar_Collab",
      "emailSubject": "quick question for you, Jack"
    },
    {
      "id": "ctel-b1-linsey-nancarrow",
      "title": "Linsey Nancarrow — ThriveKite",
      "type": "email",
      "channel": "Email",
      "status": "sent",
      "pushedDate": "Apr 2026",
      "from": "Keyona",
      "contactPerson": "Linsey Nancarrow",
      "sc_contact_id": "C1775680634421",
      "sc_initiative_id": "INI-001",
      "outreachStatus": "waiting",
      "sent": true,
      "gmailLabel": "CTEL_Webinar_Collab"
    },
    {
      "id": "ctel-b1-zareen-khan",
      "title": "Zareen Khan — Hardware Velocity",
      "type": "linkedin",
      "channel": "LinkedIn DM",
      "status": "sent",
      "pushedDate": "Apr 2026",
      "from": "Keyona",
      "contactPerson": "Zareen Khan",
      "sc_contact_id": "CTEL-zareen-khan-2026",
      "sc_initiative_id": "INI-001",
      "outreachStatus": "waiting",
      "sent": true,
      "gmailLabel": "CTEL_Webinar_Collab"
    },
    {
      "id": "ctel-b1-justin-brodie-kommit",
      "title": "Justin Brodie-Kommit — Lichen Ventures",
      "type": "linkedin",
      "channel": "LinkedIn DM",
      "status": "sent",
      "pushedDate": "Apr 2026",
      "from": "Keyona",
      "contactPerson": "Justin Brodie-Kommit",
      "sc_contact_id": "C1773968001256",
      "sc_initiative_id": "INI-001",
      "outreachStatus": "waiting",
      "sent": true,
      "gmailLabel": "CTEL_Webinar_Collab"
    },
    {
      "id": "ctel-b1-joshua-low",
      "title": "Joshua Low — Yale YPCCC",
      "type": "linkedin",
      "channel": "LinkedIn",
      "status": "pending",
      "pushedDate": "Apr 2026",
      "from": "Keyona",
      "contactPerson": "Joshua Low",
      "sc_contact_id": "CTEL-joshua-low-2026",
      "sc_initiative_id": "INI-001",
      "outreachStatus": "waiting_on_acceptance",
      "sent": false,
      "gmailLabel": "CTEL_Webinar_Collab"
    },
    {
      "id": "ctel-b1-amalia-helen",
      "title": "Amalia Helen — Independent",
      "type": "linkedin",
      "channel": "LinkedIn",
      "status": "sent",
      "pushedDate": "Apr 2026",
      "from": "Keyona",
      "contactPerson": "Amalia Helen",
      "sc_contact_id": "C1775680761534",
      "sc_initiative_id": "INI-001",
      "outreachStatus": "waiting",
      "sent": true,
      "gmailLabel": "CTEL_Webinar_Collab"
    },
    {
      "id": "ctel-b1-monica-rashkin",
      "title": "Monica Rashkin — Bright Insights",
      "type": "linkedin",
      "channel": "LinkedIn",
      "status": "pending",
      "pushedDate": "Apr 2026",
      "from": "Keyona",
      "contactPerson": "Monica Rashkin",
      "sc_contact_id": "CTEL-monica-rashkin-2026",
      "sc_initiative_id": "INI-001",
      "outreachStatus": "waiting_on_acceptance",
      "sent": false,
      "gmailLabel": "CTEL_Webinar_Collab"
    },
    {
      "id": "ctel-b1-mei-mei-whelchel",
      "title": "Mei Mei Whelchel — Clean Energy Finance",
      "type": "linkedin",
      "channel": "LinkedIn",
      "status": "pending",
      "pushedDate": "Apr 2026",
      "from": "Keyona",
      "contactPerson": "Mei Mei Whelchel",
      "sc_contact_id": "CTEL-mei-mei-whelchel-2026",
      "sc_initiative_id": "INI-001",
      "outreachStatus": "waiting_on_acceptance",
      "sent": false,
      "gmailLabel": "CTEL_Webinar_Collab"
    },
    {
      "id": "ctel-b1-thibault-boiron",
      "title": "Thibault Boiron — RESET Carbon / LRQA",
      "type": "linkedin",
      "channel": "LinkedIn",
      "status": "pending",
      "pushedDate": "Apr 2026",
      "from": "Keyona",
      "contactPerson": "Thibault Boiron",
      "sc_contact_id": "CTEL-thibault-boiron-2026",
      "sc_initiative_id": "INI-001",
      "outreachStatus": "waiting_on_acceptance",
      "sent": false,
      "gmailLabel": "CTEL_Webinar_Collab"
    },
    {
      "id": "btc-ic-email-a",
      "title": "IC Onboarding Email — Investment Committee",
      "type": "email",
      "channel": "Email",
      "status": "sent",
      "pushedDate": "Apr 2026",
      "sentDate": "Apr 9 2026",
      "from": "Keyona",
      "sc_initiative_id": "INI-001",
      "recipients": [
        { "name": "Melissa Allen", "email": "melissa@capitalmvc.com", "sc_contact_id": "C1773968002021" },
        { "name": "John Nicholson", "email": "john.nicholson@ebccanada.com", "sc_contact_id": "C1773968000038" },
        { "name": "Bryan Watson", "email": "bwatson@cleantechnorth.org", "sc_contact_id": "BTC-bryan-watson-ic-2026" },
        { "name": "Allison Gibson", "email": "allie@allieg.co", "sc_contact_id": "C1773968000041" }
      ],
      "outreachStatus": "waiting",
      "waitingOn": "Awaiting replies from IC members. Bryan Duarte sending scheduling poll now.",
      "sent": true,
      "emailSubject": "Investment Committee — first meeting, how it works, and what to expect"
    },
    {
      "id": "btc-team-intro-email-b",
      "title": "BTC Full Team Intro Email — All 8 Venture Partners",
      "type": "email",
      "channel": "Email",
      "status": "sent",
      "pushedDate": "Apr 2026",
      "sentDate": "Apr 9 2026",
      "from": "Keyona",
      "sc_initiative_id": "INI-001",
      "recipients": [
        { "name": "Jade Lockard", "email": "lockard.jade@gmail.com", "role": "Advisory Board" },
        { "name": "Nicholas Parker", "email": "nicholas@parkervm.com", "role": "Advisory Board" },
        { "name": "Marlon Thompson", "email": "marlon@openinground.co", "role": "Advisory Board" },
        { "name": "Lindsey Motlow", "email": "LEMotlow@gmail.com", "role": "Advisory Board" },
        { "name": "Melissa Allen", "email": "melissa@capitalmvc.com", "role": "Investment Committee" },
        { "name": "John Nicholson", "email": "john.nicholson@ebccanada.com", "role": "Investment Committee" },
        { "name": "Bryan Watson", "email": "bwatson@cleantechnorth.org", "role": "Investment Committee" },
        { "name": "Allison Gibson", "email": "allie@allieg.co", "role": "Investment Committee" }
      ],
      "outreachStatus": "waiting",
      "waitingOn": "Awaiting replies. June engagement meeting to follow.",
      "sent": true,
      "emailSubject": "Welcome to the BTC team — meet your fellow Venture Partners"
    },
    {
      "id": "btc-lpac-ebenezer-email-c",
      "title": "LPAC Scope Email — Ebenezer Arthur / BKR Capital",
      "type": "email",
      "channel": "Email",
      "status": "sent",
      "pushedDate": "Apr 2026",
      "sentDate": "Apr 9 2026",
      "from": "Keyona",
      "contactOrg": "BKR Capital",
      "contactPerson": "Ebenezer Arthur",
      "sc_contact_id": "C1773968000523",
      "sc_initiative_id": "INI-001",
      "outreachStatus": "waiting",
      "waitingOn": "Awaiting Ebenezer's response. Once approved, put all LPAC members on shared thread.",
      "sent": true,
      "emailSubject": "BTC Catalyst Fund — LPAC engagement overview"
    },
    {
      "id": "btc-cafiid-pipeline-001",
      "title": "CAFIID Member Pipeline — BTC ABM + Webinar + LP Sourcing",
      "type": "pipeline",
      "channel": "Multiple",
      "status": "active",
      "pushedDate": "Apr 2026",
      "from": "Keyona + Bryan Duarte",
      "sc_bucket_id": "BKT-1775753328920",
      "sc_initiative_id": "INI-1775495424026",
      "totalContacts": 107,
      "outreachStatus": "pipeline_ready",
      "nextAction": "Bryan identifies best CAFIID contact for webinar collab and sends camp-cafiid-001. Keyona begins individual ABM outreach to top-tier Enterprise members.",
      "highPriorityTargets": ["Chris Clubb (Convergence)", "Lori Trotter (Cordiant)", "Christy Sisko (CrossBoundary)", "Jacqueline Ovens (Equality Fund)", "Stephanie Emond (FinDev Canada)", "Amr Addas (Farm Credit Canada)", "Philippe Crete (Fondaction)", "Daniel Fuentes Rodriguez (Nature United)", "Jeff Cyr (Raven RIIF)", "Vivian Kotun (responsAbility)", "Patrick Hergt (Sarona)", "Adam Spence (SVX)", "Samy Derradji (Symbiotics)", "Abhisheik Dhawan (UNCDF)", "Asya Troychansky (Value for Women)", "Karim Harji (Evalysis)", "Robert Cheberiak (Desjardins)", "Mallorie Bronfman-Thomas"]
    }
  ]
}